flake8_no_types/__init__.py
flake8_no_types/py.typed
flake8_no_types-1.5.1.dist-info/LICENSE
flake8_no_types-1.5.1.dist-info/METADATA
flake8_no_types-1.5.1.dist-info/WHEEL
flake8_no_types-1.5.1.dist-info/entry_points.txt
flake8_no_types-1.5.1.dist-info/top_level.txt
flake8_no_types-1.5.1.dist-info/RECORD
