Metadata-Version: 2.1
Name: flake8-no-types
Version: 1.5.1
Summary: A flake8 plugin to ban type hints.
Home-page: https://github.com/adamchainz/flake8-no-types
Author: Adam Johnson
Author-email: me@adamj.eu
License: MIT
Project-URL: Changelog, https://github.com/adamchainz/flake8-no-types/blob/main/HISTORY.rst
Project-URL: Twitter, https://twitter.com/adamchainz
Keywords: flake8
Classifier: Development Status :: 7 - Inactive
Classifier: Framework :: Flake8
Classifier: Intended Audience :: Developers
Classifier: License :: OSI Approved :: MIT License
Classifier: Natural Language :: English
Classifier: Programming Language :: Python :: 3 :: Only
Classifier: Programming Language :: Python :: 3
Classifier: Programming Language :: Python :: 3.7
Classifier: Programming Language :: Python :: 3.8
Classifier: Programming Language :: Python :: 3.9
Classifier: Programming Language :: Python :: 3.10
Classifier: Programming Language :: Python :: 3.11
Classifier: Typing :: Typed
Requires-Python: >=3.7
License-File: LICENSE
Requires-Dist: flake8 (!=3.2.0,>=3.0)
Requires-Dist: importlib-metadata ; python_version < "3.8"
